{
    "name": "produkt1",
    "quantity":  5,
    "price": 7.99,
    "discount": false,
    "discription" : "Opis produktu1",
    "fulldiscription": "Pełny opis produktu 1",
    "imgRefs" : ["pr1_1", "pr1_2", "pr1_3"],
    "dateAdded" :""
}
{
    "name": "produkt2",
    "quantity":  10,
    "price": 12.99,
    "discount": true,
    "discription" : "Opis produktu2",
    "fulldiscription": "Pełny opis produktu 2",
    "imgRefs" : ["pr2_1", "pr2_2", "pr2_3"],
    "dateAdded" :""
}
{
    "name": "produkt3",
    "quantity":  0,
    "price": 19.99,
    "discount": false,
    "discription" : "Opis produktu3",
    "fulldiscription": "Pełny opis produktu 3",
    "imgRefs" : ["pr3_1", "pr3_2"],
    "dateAdded" :""
}
{
    "name": "produkt4",
    "quantity":  90,
    "price": 2.20,
    "discount": true,
    "discription" : "Opis produktu4",
    "fulldiscription": "Pełny opis produktu 4",
    "imgRefs" : [],
    "dateAdded" :""
}

